setup.py
couchdb_wsgi/__init__.py
couchdb_wsgi/urlencoding.py
couchdb_wsgi.egg-info/PKG-INFO
couchdb_wsgi.egg-info/SOURCES.txt
couchdb_wsgi.egg-info/dependency_links.txt
couchdb_wsgi.egg-info/top_level.txt
tests/test.py
tests/test_django.py
tests/test_webenv.py
tests/django_test/__init__.py
tests/django_test/manage.py
tests/django_test/settings.py
tests/django_test/urls.py