Metadata-Version: 1.0
Name: couchdb-wsgi
Version: 0.1
Summary: WSGI compliant handler for CouchDB external processes.
Home-page: http://github.com/mikeal/couchdb-wsgi
Author: Mikeal Rogers, Mozilla
Author-email: mikeal.rogers@gmail.com
License: http://www.mozilla.org/MPL/
Platform: Any
Classifier: Development Status :: 4 - Beta
Classifier: Environment :: Console
Classifier: Intended Audience :: Developers
Classifier: License :: OSI Approved :: Apache Software License
Classifier: Operating System :: OS Independent
Classifier: Topic :: Software Development :: Libraries :: Python Modules
